search_algorithms_pack/BinarySearch.py
search_algorithms_pack/JumpSearch.py
search_algorithms_pack/LinearSearch.py
search_algorithms_pack/__init__.py
search_algorithms_pack-0.1.1.dist-info/licenses/LICENSE
search_algorithms_pack-0.1.1.dist-info/METADATA
search_algorithms_pack-0.1.1.dist-info/WHEEL
search_algorithms_pack-0.1.1.dist-info/top_level.txt
search_algorithms_pack-0.1.1.dist-info/RECORD
