Metadata-Version: 2.4
Name: search_algorithms_pack
Version: 0.1.1
Summary: A package containing various search algorithms implementations.
Author: ARpit Kumar
Author-email: Arpit Kumar <arpitkuamr172004@gmail.com>
License: MIT License
License-File: LICENSE
Requires-Dist: sort_algorithms_pack
Dynamic: author
Dynamic: license-file
